Workbook
Name Slicer_Month: #N/A
Name Slicer_Payment_Mode: #N/A
Name Slicer_Product_Category: #N/A
Name Slicer_State: #N/A

Sheet Raw_Data
A1: Order_ID | B1: Order_Date | C1: Dispatch_Date | D1: Delivery_Date | E1: Customer_Name | F1: City | G1: State | H1: Product_Category | I1: Product_Name | J1: Quantity | K1: Unit_Price | L1: Total_Amount | M1: Payment_Mode | N1: Order_Status | O1: Delivery_Status | P1: Warehouse | Q1: Sales_Channel | R1: Return_Flag | S1: Return_Reason | T1: Delivery_Days
A2: ORD00001 | B2: 2024-10-26 | C2: 2024-10-27 | D2: 2024-10-28 | E2: Karan Gupta | F2: hyderabad | G2: Telangana | H2: Furniture | I2: Sofa | J2: 2 | K2: 100 | L2: 200 | M2: Card | N2: Pending | O2: Delayed | P2: WH-Delhi | Q2: Online | R2: No | T2: 1
A3: ORD00002 | B3: 2024-07-19 | C3: 2024-07-20 | D3: 2024-07-26 | E3: Sneha Singh | F3: PUNE | G3: Maharashtra | H3: Grocery | I3: Oil | J3: 3 | K3: 2000 | L3: 6000 | M3: Card | N3: Pending | O3: On Time | P3: WH-Delhi | Q3: Offline | R3: Yes | S3: Late Delivery | T3: 6
A4: ORD00003 | B4: 2024-10-09 | C4: 2024-10-07 | D4: 2024-10-13 | E4: Karan Yadav | F4: Jaipur | G4: Rajasthan | H4: Furniture | I4: Table | J4: 1 | K4: 500 | L4: 500 | M4: UPI | N4: Completed | O4: Delayed | P4: WH-Pune | Q4: Online | R4: Yes | T4: 6
A5: ORD00004 | B5: 2024-02-27 | C5: 2024-02-26 | D5: 2024-02-27 | E5: Neha Sharma | F5: PUNE | G5: Maharashtra | H5: Furniture | I5: Table | J5: 1 | K5: 2000 | L5: 2000 | M5: Cash | N5: Completed | O5: delayed | P5: WH-Delhi | Q5: Online | R5: No | T5: 1
A6: ORD00005 | B6: 2024-07-29 | C6: 2024-07-30 | D6: 2024-07-30 | E6: Rahul Singh | F6: Bangalore | G6: Karnataka | H6: Clothing | I6: Jeans | J6: 1 | K6: 0 | L6: 0 | M6: Card | N6: completed | O6: delayed | P6: WH-Delhi | Q6: Offline | R6: Yes | T6: 0
A7: ORD00006 | B7: 2024-06-25 | C7: 2024-06-25 | D7: 2024-06-29 | E7: Vikas Joshi | F7: Jaipur | G7: Rajasthan | H7: Grocery | I7: Rice | J7: -1 | K7: 500 | L7: -500 | M7: Cash | N7: Completed | O7: In Transit | P7: WH-Delhi | Q7: Online | R7: No | T7: 4
A8: ORD00007 | B8: 2024-01-05 | C8: 2024-01-07 | D8: 2024-01-08 | E8: Karan Yadav | F8: Jaipur | G8: Rajasthan | H8: Furniture | I8: Chair | J8: 0 | K8: 2000 | L8: 0 | M8: UPI | N8: completed | O8: delayed | P8: WH-Mumbai | Q8: Online | R8: No | T8: 1
A9: ORD00008 | B9: 2024-11-16 | C9: 2024-11-18 | D9: 2024-11-20 | E9: Sneha Patel | F9: nagpur | G9: Maharashtra | H9: Clothing | I9: T-Shirt | J9: 1 | K9: 0 | L9: 0 | M9: Card | N9: Cancelled | O9: On Time | P9: WH-Pune | Q9: Online | T9: 2
A10: ORD00009 | B10: 2024-02-24 | C10: 2024-02-22 | D10: 2024-02-27 | E10: Rahul Joshi | F10: Bangalore | G10: Karnataka | H10: Clothing | I10: T-Shirt | J10: 2 | K10: 100 | L10: 200 | M10: UPI | N10: Completed | O10: On Time | P10: WH-Pune | Q10: Online | T10: 5
A11: ORD00010 | B11: 2024-12-15 | C11: 2024-12-18 | D11: 2024-12-18 | E11: Rahul Singh | F11: PUNE | G11: Maharashtra | H11: Furniture | I11: Sofa | J11: -1 | K11: 1000 | L11: -1000 | N11: completed | O11: delayed | P11: WH-Pune | Q11: Online | R11: Yes | S11: Late Delivery | T11: 0
A12: ORD00011 | B12: 2024-10-14 | C12: 2024-10-13 | D12: 2024-10-12 | E12: Vikas Yadav | F12: hyderabad | G12: Telangana | H12: Grocery | I12: Oil | J12: 2 | K12: 2000 | L12: 4000 | N12: Completed | O12: Delayed | P12: WH-Pune | Q12: Online | R12: No | T12: -1
A13: ORD00012 | B13: 2024-06-22 | C13: 2024-06-20 | D13: 2024-06-21 | E13: Amit Gupta | F13: PUNE | G13: Maharashtra | H13: Furniture | I13: Sofa | J13: 0 | K13: 0 | L13: 295 | M13: Card | N13: Cancelled | O13: Delayed | P13: WH-Mumbai | Q13: Online | R13: Yes | S13: Late Delivery | T13: 1
A14: ORD00013 | B14: 2024-07-27 | C14: 2024-07-28 | D14: 2024-08-01 | E14: Sneha Kumar | F14: lucknow | G14: Uttar Pradesh | H14: Clothing | I14: Jacket | J14: 2 | K14: 500 | L14: 1000 | M14: UPI | N14: Completed | O14: On Time | P14: WH-Pune | Q14: Online | R14: No | T14: 4
A15: ORD00014 | B15: 2024-09-12 | C15: 2024-09-15 | D15: 2024-09-14 | E15: Neha Sharma | F15: nagpur | G15: Maharashtra | H15: Grocery | I15: Wheat | J15: -1 | K15: 1000 | L15: -1000 | N15: Pending | O15: delayed | P15: WH-Pune | Q15: Offline | T15: -1
A16: ORD00015 | B16: 2024-12-31 | C16: 2025-01-01 | D16: 2025-01-08 | E16: Vikas Patel | F16: PUNE | G16: Maharashtra | H16: Electronics | I16: Headphones | J16: 2 | K16: 100 | L16: 200 | M16: Cash | N16: Completed | O16: Delayed | P16: WH-Pune | Q16: Online | R16: Yes | T16: 7
A17: ORD00016 | B17: 2024-11-19 | C17: 2024-11-21 | D17: 2024-11-26 | E17: Anjali Singh | F17: hyderabad | G17: Telangana | H17: Clothing | I17: Jacket | J17: 2 | K17: 1000 | L17: 2000 | M17: Card | N17: completed | O17: Delayed | P17: WH-Pune | Q17: Online | R17: No | T17: 5
A18: ORD00017 | B18: 2024-02-20 | C18: 2024-02-21 | D18: 2024-02-22 | E18: Anjali Verma | F18: lucknow | G18: Uttar Pradesh | H18: Clothing | I18: T-Shirt | J18: 1 | K18: 1000 | L18: 1000 | M18: UPI | N18: Cancelled | O18: In Transit | P18: WH-Delhi | Q18: Offline | R18: No | T18: 1
A19: ORD00018 | B19: 2024-06-24 | C19: 2024-06-24 | D19: 2024-06-29 | E19: Rohit Kumar | F19: lucknow | G19: Uttar Pradesh | H19: Furniture | I19: Chair | J19: 3 | K19: 100 | L19: 300 | M19: UPI | N19: Completed | O19: On Time | P19: WH-Delhi | Q19: Offline | R19: No | T19: 5
A20: ORD00019 | B20: 2024-10-21 | C20: 2024-10-22 | D20: 2024-10-23 | E20: Vikas Joshi | F20: delhi | G20: Delhi | H20: Clothing | I20: Jacket | J20: 1 | K20: 100 | L20: 100 | M20: Cash | N20: Pending | O20: Delayed | P20: WH-Delhi | Q20: Online | R20: No | T20: 1
A21: ORD00020 | B21: 2024-03-06 | C21: 2024-03-06 | D21: 2024-03-05 | E21: Sneha Kumar | F21: Jaipur | G21: Rajasthan | H21: Clothing | I21: T-Shirt | J21: 1 | K21: 0 | L21: 0 | M21: Cash | N21: Cancelled | O21: On Time | P21: WH-Delhi | Q21: Online | R21: Yes | S21: Late Delivery | T21: -1
A22: ORD00021 | B22: 2024-01-22 | C22: 2024-01-21 | D22: 2024-01-21 | E22: Priya Singh | F22: lucknow | G22: Uttar Pradesh | H22: Electronics | I22: Headphones | J22: 3 | K22: 500 | L22: 1500 | M22: UPI | N22: Cancelled | O22: In Transit | P22: WH-Mumbai | Q22: Online | T22: 0
A23: ORD00022 | B23: 2024-05-23 | C23: 2024-05-21 | D23: 2024-05-20 | E23: Priya Singh | F23: hyderabad | G23: Telangana | H23: Clothing | I23: Jacket | J23: 3 | K23: 2000 | L23: 6000 | N23: completed | O23: delayed | P23: WH-Mumbai | Q23: Offline | T23: -1
A24: ORD00023 | B24: 2024-06-12 | C24: 2024-06-15 | D24: 2024-06-18 | E24: Pooja Verma | F24: delhi | G24: Delhi | H24: Clothing | I24: T-Shirt | J24: -1 | K24: 100 | L24: -131 | M24: Cash | N24: completed | O24: Delayed | P24: WH-Pune | Q24: Online | T24: 3
A25: ORD00024 | B25: 2024-04-17 | C25: 2024-04-17 | D25: 2024-04-19 | E25: Rahul Kumar | F25: Mumbai | G25: Maharashtra | H25: Electronics | I25: Laptop | J25: 3 | K25: 1000 | L25: 2979 | M25: Cash | N25: Completed | O25: In Transit | P25: WH-Mumbai | Q25: Offline | R25: No | T25: 2
A26: ORD00025 | B26: 2024-10-07 | C26: 2024-10-06 | D26: 2024-10-07 | E26: Sneha Sharma | F26: delhi | G26: Delhi | H26: Grocery | I26: Rice | J26: 0 | K26: 100 | L26: 0 | M26: Cash | N26: Cancelled | O26: In Transit | P26: WH-Pune | Q26: Offline | R26: Yes | S26: Late Delivery | T26: 1
A27: ORD00026 | B27: 2024-01-21 | C27: 2024-01-23 | D27: 2024-01-29 | E27: Amit Yadav | F27: Bangalore | G27: Karnataka | H27: Electronics | I27: Headphones | J27: -1 | K27: 100 | L27: -2 | M27: Card | N27: Completed | O27: Delayed | P27: WH-Mumbai | Q27: Offline | R27: No | T27: 6
A28: ORD00027 | B28: 2024-05-15 | C28: 2024-05-18 | D28: 2024-05-25 | E28: Vikas Verma | F28: hyderabad | G28: Telangana | H28: Clothing | I28: Jeans | J28: 0 | K28: 100 | L28: 0 | M28: Cash | N28: Cancelled | O28: In Transit | P28: WH-Pune | Q28: Online | T28: 7
A29: ORD00028 | B29: 2024-11-11 | C29: 2024-11-12 | D29: 2024-11-17 | E29: Rahul Yadav | F29: Jaipur | G29: Rajasthan | H29: Electronics | I29: Headphones | J29: 2 | K29: 2000 | L29: 4000 | M29: UPI | N29: completed | O29: In Transit | P29: WH-Delhi | Q29: Offline | T29: 5
A30: ORD00029 | B30: 2024-10-07 | C30: 2024-10-05 | D30: 2024-10-08 | E30: Priya Verma | F30: Jaipur | G30: Rajasthan | H30: Electronics | I30: Laptop | J30: 1 | K30: 100 | L30: 100 | M30: Cash | N30: Cancelled | O30: On Time | P30: WH-Mumbai | Q30: Offline | T30: 3
A31: ORD00030 | B31: 2024-05-26 | C31: 2024-05-27 | D31: 2024-05-26 | E31: Anjali Yadav | F31: Bangalore | G31: Karnataka | H31: Clothing | I31: Jeans | J31: 0 | K31: 2000 | L31: 0 | M31: Card | N31: Cancelled | O31: On Time | P31: WH-Delhi | Q31: Offline | R31: No | T31: -1
A32: ORD00031 | B32: 2024-10-26 | C32: 2024-10-29 | D32: 2024-11-04 | E32: Rahul Yadav | F32: PUNE | G32: Maharashtra | H32: Grocery | I32: Oil | J32: 0 | K32: 2000 | L32: 0 | M32: UPI | N32: Completed | O32: On Time | P32: WH-Mumbai | Q32: Offline | R32: No | T32: 6
A33: ORD00032 | B33: 2024-09-17 | C33: 2024-09-19 | D33: 2024-09-23 | E33: Anjali Singh | F33: nagpur | G33: Maharashtra | H33: Clothing | I33: Jacket | J33: 3 | K33: 500 | L33: 1500 | M33: UPI | N33: completed | O33: Delayed | P33: WH-Mumbai | Q33: Online | R33: No | T33: 4
A34: ORD00033 | B34: 2024-11-09 | C34: 2024-11-10 | D34: 2024-11-11 | E34: Sneha Gupta | F34: delhi | G34: Delhi | H34: Clothing | I34: Jeans | J34: 2 | K34: 2000 | L34: 4000 | M34: Cash | N34: Completed | O34: In Transit | P34: WH-Delhi | Q34: Offline | R34: No | T34: 1
A35: ORD00034 | B35: 2024-07-25 | C35: 2024-07-26 | D35: 2024-07-26 | E35: Sneha Kumar | F35: PUNE | G35: Maharashtra | H35: Grocery | I35: Rice | J35: 3 | K35: 1000 | L35: 3000 | M35: Card | N35: Completed | O35: Delayed | P35: WH-Delhi | Q35: Online | T35: 0
A36: ORD00035 | B36: 2024-05-02 | C36: 2024-05-03 | D36: 2024-05-08 | E36: Sneha Kumar | F36: hyderabad | G36: Telangana | H36: Clothing | I36: Jeans | J36: 1 | K36: 1000 | L36: 1000 | N36: Cancelled | O36: delayed | P36: WH-Pune | Q36: Online | R36: No | T36: 5
A37: ORD00036 | B37: 2024-03-25 | C37: 2024-03-27 | D37: 2024-03-31 | E37: Pooja Patel | F37: lucknow | G37: Uttar Pradesh | H37: Grocery | I37: Oil | J37: 2 | K37: 2000 | L37: 4000 | N37: Completed | O37: On Time | P37: WH-Pune | Q37: Offline | T37: 4
A38: ORD00037 | B38: 2024-07-31 | C38: 2024-08-03 | D38: 2024-08-05 | E38: Pooja Kumar | F38: Jaipur | G38: Rajasthan | H38: Clothing | I38: T-Shirt | J38: 1 | K38: 2000 | L38: 2000 | M38: Cash | N38: completed | O38: Delayed | P38: WH-Delhi | Q38: Online | R38: No | T38: 2
A39: ORD00038 | B39: 2024-06-22 | C39: 2024-06-24 | D39: 2024-06-24 | E39: Anjali Verma | F39: delhi | G39: Delhi | H39: Furniture | I39: Chair | J39: 0 | K39: 2000 | L39: 0 | M39: UPI | N39: Pending | O39: In Transit | P39: WH-Delhi | Q39: Online | R39: No | T39: 0
A40: ORD00039 | B40: 2024-06-06 | C40: 2024-06-04 | D40: 2024-06-10 | E40: Amit Verma | F40: Bangalore | G40: Karnataka | H40: Grocery | I40: Wheat | J40: 2 | K40: 2000 | L40: 4000 | M40: Cash | N40: completed | O40: Delayed | P40: WH-Delhi | Q40: Online | R40: No | T40: 6
A41: ORD00040 | B41: 2024-04-19 | C41: 2024-04-18 | D41: 2024-04-25 | E41: Amit Verma | F41: nagpur | G41: Maharashtra | H41: Electronics | I41: Mobile | J41: 1 | K41: 2000 | L41: 2000 | M41: Card | N41: Completed | O41: delayed | P41: WH-Delhi | Q41: Online | T41: 7
A42: ORD00041 | B42: 2024-11-17 | C42: 2024-11-16 | D42: 2024-11-15 | E42: Rahul Yadav | F42: nagpur | G42: Maharashtra | H42: Clothing | I42: T-Shirt | J42: -1 | K42: 500 | L42: -500 | M42: Cash | N42: completed | O42: On Time | P42: WH-Mumbai | Q42: Online | R42: Yes | T42: -1
A43: ORD00042 | B43: 2024-01-02 | C43: 2024-01-05 | D43: 2024-01-05 | E43: Priya Kumar | F43: Mumbai | G43: Maharashtra | H43: Grocery | I43: Oil | J43: 0 | K43: 1000 | L43: 33 | M43: Cash | N43: Completed | O43: On Time | P43: WH-Mumbai | Q43: Offline | T43: 0
A44: ORD00043 | B44: 2024-06-18 | C44: 2024-06-18 | D44: 2024-06-24 | E44: Anjali Joshi | F44: Mumbai | G44: Maharashtra | H44: Electronics | I44: Headphones | J44: 3 | K44: 100 | L44: 300 | M44: Card | N44: completed | O44: On Time | P44: WH-Mumbai | Q44: Offline | T44: 6
A45: ORD00044 | B45: 2024-05-23 | C45: 2024-05-23 | D45: 2024-05-26 | E45: Pooja Joshi | F45: Jaipur | G45: Rajasthan | H45: Electronics | I45: Headphones | J45: 3 | K45: 1000 | L45: 3000 | M45: UPI | N45: Pending | O45: On Time | P45: WH-Mumbai | Q45: Online | T45: 3
A46: ORD00045 | B46: 2024-11-05 | C46: 2024-11-08 | D46: 2024-11-09 | E46: Amit Singh | F46: Mumbai | G46: Maharashtra | H46: Grocery | I46: Wheat | J46: 1 | K46: 100 | L46: 100 | M46: UPI | N46: Completed | O46: In Transit | P46: WH-Delhi | Q46: Offline | R46: Yes | S46: Wrong Item | T46: 1
A47: ORD00046 | B47: 2024-12-29 | C47: 2024-12-29 | D47: 2025-01-04 | E47: Vikas Gupta | F47: lucknow | G47: Uttar Pradesh | H47: Electronics | I47: Headphones | J47: -1 | K47: 500 | L47: -500 | N47: Completed | O47: Delayed | P47: WH-Pune | Q47: Offline | R47: No | T47: 6
A48: ORD00047 | B48: 2024-03-24 | C48: 2024-03-26 | D48: 2024-03-31 | E48: Rahul Patel | F48: Mumbai | G48: Maharashtra | H48: Furniture | I48: Table | J48: 3 | K48: 500 | L48: 1500 | N48: Completed | O48: In Transit | P48: WH-Pune | Q48: Online | R48: Yes | S48: Damaged | T48: 5
A49: ORD00048 | B49: 2024-09-04 | C49: 2024-09-07 | D49: 2024-09-09 | E49: Amit Verma | F49: Mumbai | G49: Maharashtra | H49: Furniture | I49: Chair | J49: -1 | K49: 1000 | L49: -1000 | M49: Cash | N49: Cancelled | O49: In Transit | P49: WH-Pune | Q49: Offline | T49: 2
A50: ORD00049 | B50: 2024-02-23 | C50: 2024-02-25 | D50: 2024-03-02 | E50: Amit Joshi | F50: lucknow | G50: Uttar Pradesh | H50: Grocery | I50: Wheat | J50: 3 | K50: 500 | L50: 1500 | M50: Cash | N50: Completed | O50: In Transit | P50: WH-Delhi | Q50: Offline | R50: No | T50: 6
A51: ORD00050 | B51: 2024-12-10 | C51: 2024-12-13 | D51: 2024-12-19 | E51: Karan Kumar | F51: PUNE | G51: Maharashtra | H51: Clothing | I51: Jacket | J51: 1 | K51: 1000 | L51: 1000 | M51: Cash | N51: Pending | O51: Delayed | P51: WH-Delhi | Q51: Online | R51: No | T51: 6
A52: ORD00051 | B52: 2024-02-19 | C52: 2024-02-21 | D52: 2024-02-27 | E52: Pooja Sharma | F52: PUNE | G52: Maharashtra | H52: Clothing | I52: Jeans | J52: 1 | K52: 500 | L52: 102 | M52: Card | N52: Cancelled | O52: In Transit | P52: WH-Pune | Q52: Online | R52: No | T52: 6
A53: ORD00052 | B53: 2024-09-25 | C53: 2024-09-28 | D53: 2024-10-04 | E53: Priya Verma | F53: PUNE | G53: Maharashtra | H53: Clothing | I53: T-Shirt | J53: 1 | K53: 2000 | L53: 2000 | M53: Cash | N53: Pending | O53: Delayed | P53: WH-Mumbai | Q53: Online | R53: No | T53: 6
A54: ORD00053 | B54: 2024-02-19 | C54: 2024-02-17 | D54: 2024-02-17 | E54: Sneha Patel | F54: PUNE | G54: Maharashtra | H54: Clothing | I54: Jacket | J54: 1 | K54: 100 | L54: 100 | M54: Cash | N54: Cancelled | O54: On Time | P54: WH-Pune | Q54: Online | R54: No | T54: 0
A55: ORD00054 | B55: 2024-09-26 | C55: 2024-09-28 | D55: 2024-10-04 | E55: Rahul Sharma | F55: Jaipur | G55: Rajasthan | H55: Furniture | I55: Sofa | J55: 0 | K55: 2000 | L55: 0 | N55: Cancelled | O55: On Time | P55: WH-Mumbai | Q55: Offline | R55: Yes | S55: Late Delivery | T55: 6
A56: ORD00055 | B56: 2024-10-16 | C56: 2024-10-19 | D56: 2024-10-19 | E56: Neha Singh | F56: nagpur | G56: Maharashtra | H56: Furniture | I56: Chair | J56: 2 | K56: 2000 | L56: 4000 | N56: Pending | O56: Delayed | P56: WH-Pune | Q56: Offline | T56: 0
A57: ORD00056 | B57: 2024-02-25 | C57: 2024-02-26 | D57: 2024-03-04 | E57: Karan Verma | F57: nagpur | G57: Maharashtra | H57: Grocery | I57: Wheat | J57: 3 | K57: 0 | L57: 0 | M57: Cash | N57: completed | O57: On Time | P57: WH-Mumbai | Q57: Online | R57: Yes | T57: 7
A58: ORD00057 | B58: 2024-04-10 | C58: 2024-04-11 | D58: 2024-04-12 | E58: Amit Verma | F58: delhi | G58: Delhi | H58: Electronics | I58: Headphones | J58: -1 | K58: 100 | L58: -100 | M58: UPI | N58: Cancelled | O58: On Time | P58: WH-Delhi | Q58: Offline | R58: Yes | T58: 1
A59: ORD00058 | B59: 2024-10-17 | C59: 2024-10-15 | D59: 2024-10-19 | E59: Vikas Verma | F59: Mumbai | G59: Maharashtra | H59: Electronics | I59: Headphones | J59: 2 | K59: 100 | L59: 200 | M59: Cash | N59: Pending | O59: Delayed | P59: WH-Mumbai | Q59: Online | R59: Yes | T59: 4
A60: ORD00059 | B60: 2024-10-10 | C60: 2024-10-10 | D60: 2024-10-11 | E60: Rahul Verma | F60: delhi | G60: Delhi | H60: Electronics | I60: Headphones | J60: 1 | K60: 0 | L60: -243 | M60: UPI | N60: completed | O60: On Time | P60: WH-Mumbai | Q60: Online | T60: 1
A61: ORD00060 | B61: 2024-11-01 | C61: 2024-10-31 | D61: 2024-11-05 | E61: Pooja Sharma | F61: Jaipur | G61: Rajasthan | H61: Clothing | I61: Jeans | J61: 2 | K61: 2000 | L61: 4000 | M61: Cash | N61: Completed | O61: Delayed | P61: WH-Pune | Q61: Offline | T61: 5
A62: ORD00061 | B62: 2024-03-17 | C62: 2024-03-19 | D62: 2024-03-25 | E62: Priya Patel | F62: Bangalore | G62: Karnataka | H62: Electronics | I62: Laptop | J62: 3 | K62: 100 | L62: 300 | M62: UPI | N62: Pending | O62: On Time | P62: WH-Pune | Q62: Offline | R62: Yes | T62: 6
A63: ORD00062 | B63: 2024-11-18 | C63: 2024-11-17 | D63: 2024-11-19 | E63: Neha Joshi | F63: delhi | G63: Delhi | H63: Electronics | I63: Mobile | J63: 2 | K63: 0 | L63: 0 | M63: UPI | N63: completed | O63: In Transit | P63: WH-Delhi | Q63: Online | R63: No | T63: 2
A64: ORD00063 | B64: 2024-05-07 | C64: 2024-05-09 | D64: 2024-05-16 | E64: Priya Verma | F64: delhi | G64: Delhi | H64: Clothing | I64: Jacket | J64: 0 | K64: 1000 | L64: 0 | M64: Card | N64: Pending | O64: In Transit | P64: WH-Pune | Q64: Offline | R64: No | T64: 7
A65: ORD00064 | B65: 2024-04-19 | C65: 2024-04-21 | D65: 2024-04-27 | E65: Anjali Singh | F65: delhi | G65: Delhi | H65: Clothing | I65: Jeans | J65: 3 | K65: 2000 | L65: 6000 | N65: Pending | O65: delayed | P65: WH-Delhi | Q65: Online | R65: No | T65: 6
A66: ORD00065 | B66: 2024-08-18 | C66: 2024-08-18 | D66: 2024-08-23 | E66: Amit Singh | F66: Mumbai | G66: Maharashtra | H66: Clothing | I66: Jeans | J66: -1 | K66: 1000 | L66: -1000 | N66: completed | O66: In Transit | P66: WH-Pune | Q66: Online | T66: 5
A67: ORD00066 | B67: 2024-03-18 | C67: 2024-03-19 | D67: 2024-03-24 | E67: Rohit Joshi | F67: Mumbai | G67: Maharashtra | H67: Clothing | I67: Jacket | J67: 3 | K67: 0 | L67: 0 | N67: completed | O67: Delayed | P67: WH-Pune | Q67: Offline | R67: Yes | S67: Late Delivery | T67: 5
A68: ORD00067 | B68: 2024-07-04 | C68: 2024-07-04 | D68: 2024-07-09 | E68: Rohit Joshi | F68: Bangalore | G68: Karnataka | H68: Electronics | I68: Laptop | J68: 1 | K68: 0 | L68: 0 | N68: Pending | O68: Delayed | P68: WH-Mumbai | Q68: Offline | T68: 5
A69: ORD00068 | B69: 2024-08-26 | C69: 2024-08-27 | D69: 2024-09-02 | E69: Pooja Sharma | F69: Mumbai | G69: Maharashtra | H69: Electronics | I69: Headphones | J69: 1 | K69: 100 | L69: 100 | M69: Cash | N69: Pending | O69: In Transit | P69: WH-Pune | Q69: Online | R69: No | T69: 6
A70: ORD00069 | B70: 2024-10-20 | C70: 2024-10-18 | D70: 2024-10-25 | E70: Sneha Gupta | F70: hyderabad | G70: Telangana | H70: Grocery | I70: Rice | J70: 1 | K70: 100 | L70: 100 | M70: Cash | N70: Pending | O70: On Time | P70: WH-Mumbai | Q70: Offline | R70: Yes | S70: Damaged | T70: 7
A71: ORD00070 | B71: 2024-10-31 | C71: 2024-10-29 | D71: 2024-11-02 | E71: Rohit Sharma | F71: PUNE | G71: Maharashtra | H71: Electronics | I71: Laptop | J71: 0 | K71: 0 | L71: 0 | M71: UPI | N71: Cancelled | O71: On Time | P71: WH-Mumbai | Q71: Offline | R71: Yes | S71: Wrong Item | T71: 4
A72: ORD00071 | B72: 2024-12-08 | C72: 2024-12-09 | D72: 2024-12-13 | E72: Sneha Gupta | F72: Mumbai | G72: Maharashtra | H72: Clothing | I72: T-Shirt | J72: 3 | K72: 100 | L72: 300 | M72: UPI | N72: Completed | O72: In Transit | P72: WH-Mumbai | Q72: Offline | R72: Yes | S72: Late Delivery | T72: 4
A73: ORD00072 | B73: 2024-10-16 | C73: 2024-10-14 | D73: 2024-10-19 | E73: Anjali Sharma | F73: Bangalore | G73: Karnataka | H73: Furniture | I73: Sofa | J73: 0 | K73: 100 | L73: 0 | M73: Card | N73: Completed | O73: In Transit | P73: WH-Mumbai | Q73: Offline | T73: 5
A74: ORD00073 | B74: 2024-04-06 | C74: 2024-04-08 | D74: 2024-04-07 | E74: Karan Kumar | F74: lucknow | G74: Uttar Pradesh | H74: Furniture | I74: Chair | J74: 2 | K74: 1000 | L74: 1855 | M74: Card | N74: Completed | O74: delayed | P74: WH-Delhi | Q74: Offline | T74: -1
A75: ORD00074 | B75: 2024-08-06 | C75: 2024-08-08 | D75: 2024-08-13 | E75: Sneha Verma | F75: Jaipur | G75: Rajasthan | H75: Grocery | I75: Wheat | J75: 1 | K75: 2000 | L75: 2000 | M75: UPI | N75: Cancelled | O75: Delayed | P75: WH-Mumbai | Q75: Offline | R75: Yes | S75: Late Delivery | T75: 5
A76: ORD00075 | B76: 2024-07-20 | C76: 2024-07-21 | D76: 2024-07-25 | E76: Rohit Yadav | F76: Bangalore | G76: Karnataka | H76: Electronics | I76: Mobile | J76: 1 | K76: 100 | L76: 100 | M76: Cash | N76: Pending | O76: In Transit | P76: WH-Pune | Q76: Offline | R76: No | T76: 4
A77: ORD00076 | B77: 2024-02-28 | C77: 2024-02-27 | D77: 2024-03-05 | E77: Pooja Patel | F77: Bangalore | G77: Karnataka | H77: Electronics | I77: Laptop | J77: 0 | K77: 500 | L77: 0 | N77: Pending | O77: delayed | P77: WH-Pune | Q77: Offline | R77: No | T77: 7
A78: ORD00077 | B78: 2024-05-21 | C78: 2024-05-24 | D78: 2024-05-26 | E78: Rohit Patel | F78: Bangalore | G78: Karnataka | H78: Electronics | I78: Mobile | J78: 3 | K78: 500 | L78: 1500 | M78: UPI | N78: Cancelled | O78: Delayed | P78: WH-Pune | Q78: Online | R78: Yes | T78: 2
A79: ORD00078 | B79: 2024-12-10 | C79: 2024-12-08 | D79: 2024-12-11 | E79: Pooja Gupta | F79: Mumbai | G79: Maharashtra | H79: Furniture | I79: Sofa | J79: 0 | K79: 500 | L79: 0 | N79: Completed | O79: On Time | P79: WH-Pune | Q79: Offline | R79: Yes | S79: Wrong Item | T79: 3
A80: ORD00079 | B80: 2024-10-08 | C80: 2024-10-11 | D80: 2024-10-15 | E80: Rohit Singh | F80: delhi | G80: Delhi | H80: Grocery | I80: Oil | J80: -1 | K80: 100 | L80: -100 | M80: UPI | N80: Cancelled | O80: delayed | P80: WH-Pune | Q80: Offline | T80: 4
A81: ORD00080 | B81: 2024-11-24 | C81: 2024-11-25 | D81: 2024-11-24 | E81: Neha Gupta | F81: Bangalore | G81: Karnataka | H81: Furniture | I81: Table | J81: 3 | K81: 0 | L81: 0 | M81: Cash | N81: completed | O81: In Transit | P81: WH-Pune | Q81: Online | R81: No | T81: -1
A82: ORD00081 | B82: 2024-05-19 | C82: 2024-05-19 | D82: 2024-05-19 | E82: Karan Sharma | F82: PUNE | G82: Maharashtra | H82: Clothing | I82: Jacket | J82: -1 | K82: 500 | L82: -500 | M82: Card | N82: Pending | O82: delayed | P82: WH-Mumbai | Q82: Online | T82: 0
A83: ORD00082 | B83: 2024-01-04 | C83: 2024-01-03 | D83: 2024-01-04 | E83: Amit Kumar | F83: Bangalore | G83: Karnataka | H83: Grocery | I83: Rice | J83: 2 | K83: 2000 | L83: 4000 | M83: Card | N83: Pending | O83: On Time | P83: WH-Pune | Q83: Offline | T83: 1
A84: ORD00083 | B84: 2024-04-26 | C84: 2024-04-24 | D84: 2024-04-27 | E84: Rahul Yadav | F84: PUNE | G84: Maharashtra | H84: Furniture | I84: Chair | J84: -1 | K84: 100 | L84: -100 | M84: Card | N84: Completed | O84: On Time | P84: WH-Delhi | Q84: Offline | R84: No | T84: 3
A85: ORD00084 | B85: 2024-06-07 | C85: 2024-06-06 | D85: 2024-06-05 | E85: Vikas Singh | F85: PUNE | G85: Maharashtra | H85: Clothing | I85: T-Shirt | J85: 1 | K85: 2000 | L85: 2000 | M85: Cash | N85: Completed | O85: In Transit | P85: WH-Pune | Q85: Online | R85: Yes | S85: Late Delivery | T85: -1
A86: ORD00085 | B86: 2024-10-22 | C86: 2024-10-21 | D86: 2024-10-26 | E86: Vikas Yadav | F86: PUNE | G86: Maharashtra | H86: Grocery | I86: Wheat | J86: 3 | K86: 2000 | L86: 6000 | M86: Card | N86: Cancelled | O86: On Time | P86: WH-Mumbai | Q86: Offline | R86: No | T86: 5
A87: ORD00086 | B87: 2024-10-22 | C87: 2024-10-25 | D87: 2024-10-28 | E87: Amit Joshi | F87: Jaipur | G87: Rajasthan | H87: Electronics | I87: Mobile | J87: 1 | K87: 1000 | L87: 1000 | M87: Card | N87: Pending | O87: In Transit | P87: WH-Mumbai | Q87: Offline | R87: No | T87: 3
A88: ORD00087 | B88: 2024-09-24 | C88: 2024-09-22 | D88: 2024-09-25 | E88: Sneha Patel | F88: Mumbai | G88: Maharashtra | H88: Clothing | I88: Jacket | J88: 2 | K88: 500 | L88: 1000 | N88: Pending | O88: Delayed | P88: WH-Delhi | Q88: Offline | R88: Yes | T88: 3
A89: ORD00088 | B89: 2024-12-11 | C89: 2024-12-12 | D89: 2024-12-15 | E89: Priya Gupta | F89: nagpur | G89: Maharashtra | H89: Clothing | I89: Jeans | J89: 2 | K89: 1000 | L89: 2000 | M89: UPI | N89: Pending | O89: Delayed | P89: WH-Mumbai | Q89: Online | R89: No | T89: 3
A90: ORD00089 | B90: 2024-04-14 | C90: 2024-04-15 | D90: 2024-04-21 | E90: Sneha Joshi | F90: Bangalore | G90: Karnataka | H90: Electronics | I90: Laptop | J90: -1 | K90: 100 | L90: -100 | M90: Card | N90: Pending | O90: Delayed | P90: WH-Delhi | Q90: Online | T90: 6
A91: ORD00090 | B91: 2024-05-28 | C91: 2024-05-28 | D91: 2024-05-31 | E91: Neha Singh | F91: Bangalore | G91: Karnataka | H91: Grocery | I91: Wheat | J91: 3 | K91: 2000 | L91: 6155 | M91: Card | N91: Pending | O91: In Transit | P91: WH-Mumbai | Q91: Online | R91: No | T91: 3
A92: ORD00091 | B92: 2024-07-20 | C92: 2024-07-21 | D92: 2024-07-24 | E92: Rohit Yadav | F92: Bangalore | G92: Karnataka | H92: Furniture | I92: Table | J92: -1 | K92: 2000 | L92: -2000 | M92: Cash | N92: Completed | O92: In Transit | P92: WH-Delhi | Q92: Offline | R92: Yes | T92: 3
A93: ORD00092 | B93: 2024-05-11 | C93: 2024-05-11 | D93: 2024-05-16 | E93: Karan Gupta | F93: Mumbai | G93: Maharashtra | H93: Furniture | I93: Table | J93: 1 | K93: 100 | L93: 100 | N93: Cancelled | O93: On Time | P93: WH-Delhi | Q93: Offline | R93: No | T93: 5
A94: ORD00093 | B94: 2024-04-13 | C94: 2024-04-15 | D94: 2024-04-21 | E94: Rohit Gupta | F94: Bangalore | G94: Karnataka | H94: Electronics | I94: Laptop | J94: 1 | K94: 1000 | L94: 1000 | M94: UPI | N94: Cancelled | O94: In Transit | P94: WH-Delhi | Q94: Offline | R94: No | T94: 6
A95: ORD00094 | B95: 2024-03-03 | C95: 2024-03-04 | D95: 2024-03-11 | E95: Anjali Yadav | F95: lucknow | G95: Uttar Pradesh | H95: Furniture | I95: Chair | J95: 3 | K95: 0 | L95: 0 | N95: Completed | O95: Delayed | P95: WH-Delhi | Q95: Online | R95: Yes | S95: Damaged | T95: 7
A96: ORD00095 | B96: 2024-09-21 | C96: 2024-09-22 | D96: 2024-09-27 | E96: Neha Kumar | F96: delhi | G96: Delhi | H96: Grocery | I96: Wheat | J96: 2 | K96: 500 | L96: 1000 | M96: UPI | N96: completed | O96: Delayed | P96: WH-Mumbai | Q96: Online | T96: 5
A97: ORD00096 | B97: 2024-05-03 | C97: 2024-05-01 | D97: 2024-05-05 | E97: Vikas Patel | F97: Jaipur | G97: Rajasthan | H97: Grocery | I97: Wheat | J97: 0 | K97: 2000 | L97: 0 | N97: Cancelled | O97: Delayed | P97: WH-Mumbai | Q97: Online | R97: Yes | T97: 4
A98: ORD00097 | B98: 2024-09-15 | C98: 2024-09-16 | D98: 2024-09-17 | E98: Anjali Patel | F98: Bangalore | G98: Karnataka | H98: Electronics | I98: Laptop | J98: 1 | K98: 500 | L98: 500 | M98: UPI | N98: Completed | O98: In Transit | P98: WH-Delhi | Q98: Offline | R98: Yes | T98: 1
A99: ORD00098 | B99: 2024-09-15 | C99: 2024-09-15 | D99: 2024-09-18 | E99: Sneha Patel | F99: delhi | G99: Delhi | H99: Electronics | I99: Headphones | J99: -1 | K99: 0 | L99: 0 | M99: Cash | N99: Cancelled | O99: On Time | P99: WH-Delhi | Q99: Offline | R99: No | T99: 3
A100: ORD00099 | B100: 2024-08-11 | C100: 2024-08-13 | D100: 2024-08-19 | E100: Neha Yadav | F100: PUNE | G100: Maharashtra | H100: Grocery | I100: Wheat | J100: 1 | K100: 0 | L100: 0 | M100: UPI | N100: Pending | O100: delayed | P100: WH-Pune | Q100: Online | R100: Yes | S100: Damaged | T100: 6
...

Sheet Clean_data
A1: Order_ID | B1: Order_Date | C1: Dispatch_Date | D1: Delivery_Date | E1: Customer_Name | F1: City | G1: State | H1: Product_Category | I1: Product_Name | J1: Quantity | K1: Unit_Price | L1: Total_Amount | M1: Payment_Mode | N1: Order_Status | O1: Delivery_Status | P1: Warehouse | Q1: Sales_Channel | R1: Return_Flag | S1: Return_Reason | T1: Delivery_Days | U1: Duplicate check | V1: Qty_Check_Status | W1: Unit_Price_Status | X1: Date_Status | Y1: Price_Check | Z1: Amount check | AA1: Final_Amount | AB1: Payment_Mode_check | AC1: Final_return_flag
A2: ORD00001 | B2: {=DATEVALUE(VLOOKUP(A2,Raw_Data!A1:D2001,{2,3,4},0))} -> 45591 | C2: 45592 | D2: 45593 | E2: Karan Gupta | F2: Hyderabad | G2: Telangana | H2: Furniture | I2: Sofa | J2: 2 | K2: 100 | L2: =J2*K2 -> 200 | M2: Card | N2: Pending | O2: Delayed | P2: WH-Delhi | Q2: Online | R2: No | S2: Late Delivery | T2: 1 | U2: =IF(COUNTIF(A2:A2001,A2)=1,"Keep","Duplicate") -> Keep | V2: =IF(J2<=0,"Fix","Ok") -> Ok | W2: =IF(Raw_Data!K2=0,"Missing","Valid") -> Valid | X2: =IF(C2<B2,"Dispatch Error",IF(D2<B2,"Delivery Before Order",IF(D2<C2,"Delivery Before Dispatch","OK"))) -> OK | Y2: =IF(K2<=0,"Fix","Ok") -> Ok | Z2: =IF(L2="","Blank",IF(L2=J2*K2,"Ok","Wrong")) -> Ok | AA2: =IF(OR(L2="",L2<>J2*K2),J2*K2,L2) -> 200 | AB2: =IF(M2="","Missing","ok") -> ok | AC2: =IF(R2="No","Not Returned",IF(R2="Yes",IF(S2="","Unknown",S2),IF(L2<0,"Wrong",IF(OR(O2="Delayed",O2="In Transit",O2="On Time"),"Not Returned","")))) -> Not Returned
A3: ORD00002 | B3: {=DATEVALUE(VLOOKUP(A3,Raw_Data!A2:D2002,{2,3,4},0))} -> 45492 | C3: 45493 | D3: 45499 | E3: Sneha Singh | F3: Pune | G3: Maharashtra | H3: Grocery | I3: Oil | J3: 3 | K3: 2000 | L3: =J3*K3 -> 6000 | M3: Card | N3: Pending | O3: On Time | P3: WH-Delhi | Q3: Offline | R3: Yes | S3: Late Delivery | T3: 6 | U3: =IF(COUNTIF(A3:A2002,A3)=1,"Keep","Duplicate") -> Keep | V3: =IF(J3<=0,"Fix","Ok") -> Ok | W3: =IF(Raw_Data!K3=0,"Missing","Valid") -> Valid | X3: =IF(C3<B3,"Dispatch Error",IF(D3<B3,"Delivery Before Order",IF(D3<C3,"Delivery Before Dispatch","OK"))) -> OK | Y3: =IF(K3<=0,"Fix","Ok") -> Ok | Z3: =IF(L3="","Blank",IF(L3=J3*K3,"Ok","Wrong")) -> Ok | AA3: =IF(OR(L3="",L3<>J3*K3),J3*K3,L3) -> 6000 | AB3: =IF(M3="","Missing","ok") -> ok | AC3: =IF(R3="No","Not Returned",IF(R3="Yes",IF(S3="","Unknown",S3),IF(L3<0,"Wrong",IF(OR(O3="Delayed",O3="In Transit",O3="On Time"),"Not Returned","")))) -> Late Delivery
A4: ORD00003 | B4: {=DATEVALUE(VLOOKUP(A4,Raw_Data!A3:D2003,{2,3,4},0))} -> 45574 | C4: 45572 | D4: 45578 | E4: Karan Yadav | F4: Jaipur | G4: Rajasthan | H4: Furniture | I4: Table | J4: 1 | K4: 500 | L4: =J4*K4 -> 500 | M4: UPI | N4: Completed | O4: Delayed | P4: WH-Pune | Q4: Online | R4: Yes | S4: Late Delivery | T4: 6 | U4: =IF(COUNTIF(A4:A2003,A4)=1,"Keep","Duplicate") -> Keep | V4: =IF(J4<=0,"Fix","Ok") -> Ok | W4: =IF(Raw_Data!K4=0,"Missing","Valid") -> Valid | X4: =IF(C4<B4,"Dispatch Error",IF(D4<B4,"Delivery Before Order",IF(D4<C4,"Delivery Before Dispatch","OK"))) -> Dispatch Error | Y4: =IF(K4<=0,"Fix","Ok") -> Ok | Z4: =IF(L4="","Blank",IF(L4=J4*K4,"Ok","Wrong")) -> Ok | AA4: =IF(OR(L4="",L4<>J4*K4),J4*K4,L4) -> 500 | AB4: =IF(M4="","Missing","ok") -> ok | AC4: =IF(R4="No","Not Returned",IF(R4="Yes",IF(S4="","Unknown",S4),IF(L4<0,"Wrong",IF(OR(O4="Delayed",O4="In Transit",O4="On Time"),"Not Returned","")))) -> Late Delivery
A5: ORD00004 | B5: {=DATEVALUE(VLOOKUP(A5,Raw_Data!A4:D2004,{2,3,4},0))} -> 45349 | C5: 45348 | D5: 45349 | E5: Neha Sharma | F5: Pune | G5: Maharashtra | H5: Furniture | I5: Table | J5: 1 | K5: 2000 | L5: =J5*K5 -> 2000 | M5: Cash | N5: Completed | O5: Delayed | P5: WH-Delhi | Q5: Online | R5: No | S5: Late Delivery | T5: 1 | U5: =IF(COUNTIF(A5:A2004,A5)=1,"Keep","Duplicate") -> Keep | V5: =IF(J5<=0,"Fix","Ok") -> Ok | W5: =IF(Raw_Data!K5=0,"Missing","Valid") -> Valid | X5: =IF(C5<B5,"Dispatch Error",IF(D5<B5,"Delivery Before Order",IF(D5<C5,"Delivery Before Dispatch","OK"))) -> Dispatch Error | Y5: =IF(K5<=0,"Fix","Ok") -> Ok | Z5: =IF(L5="","Blank",IF(L5=J5*K5,"Ok","Wrong")) -> Ok | AA5: =IF(OR(L5="",L5<>J5*K5),J5*K5,L5) -> 2000 | AB5: =IF(M5="","Missing","ok") -> ok | AC5: =IF(R5="No","Not Returned",IF(R5="Yes",IF(S5="","Unknown",S5),IF(L5<0,"Wrong",IF(OR(O5="Delayed",O5="In Transit",O5="On Time"),"Not Returned","")))) -> Not Returned
A6: ORD00005 | B6: {=DATEVALUE(VLOOKUP(A6,Raw_Data!A5:D2005,{2,3,4},0))} -> 45502 | C6: 45503 | D6: 45503 | E6: Rahul Singh | F6: Bangalore | G6: Karnataka | H6: Clothing | I6: Jeans | J6: 1 | K6: 0 | L6: =J6*K6 -> 0 | M6: Card | N6: Completed | O6: delayed | P6: WH-Delhi | Q6: Offline | R6: Yes | S6: Late Delivery | T6: 0 | U6: =IF(COUNTIF(A6:A2005,A6)=1,"Keep","Duplicate") -> Keep | V6: =IF(J6<=0,"Fix","Ok") -> Ok | W6: =IF(Raw_Data!K6=0,"Missing","Valid") -> Missing | X6: =IF(C6<B6,"Dispatch Error",IF(D6<B6,"Delivery Before Order",IF(D6<C6,"Delivery Before Dispatch","OK"))) -> OK | Y6: =IF(K6<=0,"Fix","Ok") -> Fix | Z6: =IF(L6="","Blank",IF(L6=J6*K6,"Ok","Wrong")) -> Ok | AA6: =IF(OR(L6="",L6<>J6*K6),J6*K6,L6) -> 0 | AB6: =IF(M6="","Missing","ok") -> ok | AC6: =IF(R6="No","Not Returned",IF(R6="Yes",IF(S6="","Unknown",S6),IF(L6<0,"Wrong",IF(OR(O6="Delayed",O6="In Transit",O6="On Time"),"Not Returned","")))) -> Late Delivery
A7: ORD00006 | B7: {=DATEVALUE(VLOOKUP(A7,Raw_Data!A6:D2006,{2,3,4},0))} -> 45468 | C7: 45468 | D7: 45472 | E7: Vikas Joshi | F7: Jaipur | G7: Rajasthan | H7: Grocery | I7: Rice | J7: -1 | K7: 500 | L7: =J7*K7 -> -500 | M7: Cash | N7: Completed | O7: In Transit | P7: WH-Delhi | Q7: Online | R7: No | S7: Late Delivery | T7: 4 | U7: =IF(COUNTIF(A7:A2006,A7)=1,"Keep","Duplicate") -> Keep | V7: =IF(J7<=0,"Fix","Ok") -> Fix | W7: =IF(Raw_Data!K7=0,"Missing","Valid") -> Valid | X7: =IF(C7<B7,"Dispatch Error",IF(D7<B7,"Delivery Before Order",IF(D7<C7,"Delivery Before Dispatch","OK"))) -> OK | Y7: =IF(K7<=0,"Fix","Ok") -> Ok | Z7: =IF(L7="","Blank",IF(L7=J7*K7,"Ok","Wrong")) -> Ok | AA7: =IF(OR(L7="",L7<>J7*K7),J7*K7,L7) -> -500 | AB7: =IF(M7="","Missing","ok") -> ok | AC7: =IF(R7="No","Not Returned",IF(R7="Yes",IF(S7="","Unknown",S7),IF(L7<0,"Wrong",IF(OR(O7="Delayed",O7="In Transit",O7="On Time"),"Not Returned","")))) -> Not Returned
A8: ORD00007 | B8: {=DATEVALUE(VLOOKUP(A8,Raw_Data!A7:D2007,{2,3,4},0))} -> 45296 | C8: 45298 | D8: 45299 | E8: Karan Yadav | F8: Jaipur | G8: Rajasthan | H8: Furniture | I8: Chair | J8: 0 | K8: 2000 | L8: =J8*K8 -> 0 | M8: UPI | N8: Completed | O8: Delayed | P8: WH-Mumbai | Q8: Online | R8: No | S8: Late Delivery | T8: 1 | U8: =IF(COUNTIF(A8:A2007,A8)=1,"Keep","Duplicate") -> Keep | V8: =IF(J8<=0,"Fix","Ok") -> Fix | W8: =IF(Raw_Data!K8=0,"Missing","Valid") -> Valid | X8: =IF(C8<B8,"Dispatch Error",IF(D8<B8,"Delivery Before Order",IF(D8<C8,"Delivery Before Dispatch","OK"))) -> OK | Y8: =IF(K8<=0,"Fix","Ok") -> Ok | Z8: =IF(L8="","Blank",IF(L8=J8*K8,"Ok","Wrong")) -> Ok | AA8: =IF(OR(L8="",L8<>J8*K8),J8*K8,L8) -> 0 | AB8: =IF(M8="","Missing","ok") -> ok | AC8: =IF(R8="No","Not Returned",IF(R8="Yes",IF(S8="","Unknown",S8),IF(L8<0,"Wrong",IF(OR(O8="Delayed",O8="In Transit",O8="On Time"),"Not Returned","")))) -> Not Returned
A9: ORD00008 | B9: {=DATEVALUE(VLOOKUP(A9,Raw_Data!A8:D2008,{2,3,4},0))} -> 45612 | C9: 45614 | D9: 45616 | E9: Sneha Patel | F9: Nagpur | G9: Maharashtra | H9: Clothing | I9: T-Shirt | J9: 1 | K9: 0 | L9: =J9*K9 -> 0 | M9: Card | N9: Cancelled | O9: On Time | P9: WH-Pune | Q9: Online | R9: yes | S9: Late Delivery | T9: 2 | U9: =IF(COUNTIF(A9:A2008,A9)=1,"Keep","Duplicate") -> Keep | V9: =IF(J9<=0,"Fix","Ok") -> Ok | W9: =IF(Raw_Data!K9=0,"Missing","Valid") -> Missing | X9: =IF(C9<B9,"Dispatch Error",IF(D9<B9,"Delivery Before Order",IF(D9<C9,"Delivery Before Dispatch","OK"))) -> OK | Y9: =IF(K9<=0,"Fix","Ok") -> Fix | Z9: =IF(L9="","Blank",IF(L9=J9*K9,"Ok","Wrong")) -> Ok | AA9: =IF(OR(L9="",L9<>J9*K9),J9*K9,L9) -> 0 | AB9: =IF(M9="","Missing","ok") -> ok | AC9: =IF(R9="No","Not Returned",IF(R9="Yes",IF(S9="","Unknown",S9),IF(L9<0,"Wrong",IF(OR(O9="Delayed",O9="In Transit",O9="On Time"),"Not Returned","")))) -> Late Delivery
A10: ORD00009 | B10: {=DATEVALUE(VLOOKUP(A10,Raw_Data!A9:D2009,{2,3,4},0))} -> 45346 | C10: 45344 | D10: 45349 | E10: Rahul Joshi | F10: Bangalore | G10: Karnataka | H10: Clothing | I10: T-Shirt | J10: 2 | K10: 100 | L10: =J10*K10 -> 200 | M10: UPI | N10: Completed | O10: On Time | P10: WH-Pune | Q10: Online | R10: yes | S10: Late Delivery | T10: 5 | U10: =IF(COUNTIF(A10:A2009,A10)=1,"Keep","Duplicate") -> Keep | V10: =IF(J10<=0,"Fix","Ok") -> Ok | W10: =IF(Raw_Data!K10=0,"Missing","Valid") -> Valid | X10: =IF(C10<B10,"Dispatch Error",IF(D10<B10,"Delivery Before Order",IF(D10<C10,"Delivery Before Dispatch","OK"))) -> Dispatch Error | Y10: =IF(K10<=0,"Fix","Ok") -> Ok | Z10: =IF(L10="","Blank",IF(L10=J10*K10,"Ok","Wrong")) -> Ok | AA10: =IF(OR(L10="",L10<>J10*K10),J10*K10,L10) -> 200 | AB10: =IF(M10="","Missing","ok") -> ok | AC10: =IF(R10="No","Not Returned",IF(R10="Yes",IF(S10="","Unknown",S10),IF(L10<0,"Wrong",IF(OR(O10="Delayed",O10="In Transit",O10="On Time"),"Not Returned","")))) -> Late Delivery
A11: ORD00010 | B11: {=DATEVALUE(VLOOKUP(A11,Raw_Data!A10:D2010,{2,3,4},0))} -> 45641 | C11: 45644 | D11: 45644 | E11: Rahul Singh | F11: Pune | G11: Maharashtra | H11: Furniture | I11: Sofa | J11: -1 | K11: 1000 | L11: =J11*K11 -> -1000 | M11: Unknown | N11: Completed | O11: Delayed | P11: WH-Pune | Q11: Online | R11: Yes | S11: Late Delivery | T11: 0 | U11: =IF(COUNTIF(A11:A2010,A11)=1,"Keep","Duplicate") -> Keep | V11: =IF(J11<=0,"Fix","Ok") -> Fix | W11: =IF(Raw_Data!K11=0,"Missing","Valid") -> Valid | X11: =IF(C11<B11,"Dispatch Error",IF(D11<B11,"Delivery Before Order",IF(D11<C11,"Delivery Before Dispatch","OK"))) -> OK | Y11: =IF(K11<=0,"Fix","Ok") -> Ok | Z11: =IF(L11="","Blank",IF(L11=J11*K11,"Ok","Wrong")) -> Ok | AA11: =IF(OR(L11="",L11<>J11*K11),J11*K11,L11) -> -1000 | AB11: =IF(M11="","Missing","ok") -> ok | AC11: =IF(R11="No","Not Returned",IF(R11="Yes",IF(S11="","Unknown",S11),IF(L11<0,"Wrong",IF(OR(O11="Delayed",O11="In Transit",O11="On Time"),"Not Returned","")))) -> Late Delivery
A12: ORD00011 | B12: {=DATEVALUE(VLOOKUP(A12,Raw_Data!A11:D2011,{2,3,4},0))} -> 45579 | C12: 45578 | D12: 45577 | E12: Vikas Yadav | F12: Hyderabad | G12: Telangana | H12: Grocery | I12: Oil | J12: 2 | K12: 2000 | L12: =J12*K12 -> 4000 | M12: Unknown | N12: Completed | O12: Delayed | P12: WH-Pune | Q12: Online | R12: No | S12: N/A | T12: -1 | U12: =IF(COUNTIF(A12:A2011,A12)=1,"Keep","Duplicate") -> Keep | V12: =IF(J12<=0,"Fix","Ok") -> Ok | W12: =IF(Raw_Data!K12=0,"Missing","Valid") -> Valid | X12: =IF(C12<B12,"Dispatch Error",IF(D12<B12,"Delivery Before Order",IF(D12<C12,"Delivery Before Dispatch","OK"))) -> Dispatch Error | Y12: =IF(K12<=0,"Fix","Ok") -> Ok | Z12: =IF(L12="","Blank",IF(L12=J12*K12,"Ok","Wrong")) -> Ok | AA12: =IF(OR(L12="",L12<>J12*K12),J12*K12,L12) -> 4000 | AB12: =IF(M12="","Missing","ok") -> ok | AC12: =IF(R12="No","Not Returned",IF(R12="Yes",IF(S12="","Unknown",S12),IF(L12<0,"Wrong",IF(OR(O12="Delayed",O12="In Transit",O12="On Time"),"Not Returned","")))) -> Not Returned
A13: ORD00012 | B13: {=DATEVALUE(VLOOKUP(A13,Raw_Data!A12:D2012,{2,3,4},0))} -> 45465 | C13: 45463 | D13: 45464 | E13: Amit Gupta | F13: Pune | G13: Maharashtra | H13: Furniture | I13: Sofa | J13: 0 | K13: 0 | L13: =J13*K13 -> 0 | M13: Card | N13: Cancelled | O13: Delayed | P13: WH-Mumbai | Q13: Online | R13: Yes | S13: Late Delivery | T13: 1 | U13: =IF(COUNTIF(A13:A2012,A13)=1,"Keep","Duplicate") -> Keep | V13: =IF(J13<=0,"Fix","Ok") -> Fix | W13: =IF(Raw_Data!K13=0,"Missing","Valid") -> Missing | X13: =IF(C13<B13,"Dispatch Error",IF(D13<B13,"Delivery Before Order",IF(D13<C13,"Delivery Before Dispatch","OK"))) -> Dispatch Error | Y13: =IF(K13<=0,"Fix","Ok") -> Fix | Z13: =IF(L13="","Blank",IF(L13=J13*K13,"Ok","Wrong")) -> Ok | AA13: =IF(OR(L13="",L13<>J13*K13),J13*K13,L13) -> 0 | AB13: =IF(M13="","Missing","ok") -> ok | AC13: =IF(R13="No","Not Returned",IF(R13="Yes",IF(S13="","Unknown",S13),IF(L13<0,"Wrong",IF(OR(O13="Delayed",O13="In Transit",O13="On Time"),"Not Returned","")))) -> Late Delivery
... A2001: ORD02000 | B2001: {=DATEVALUE(VLOOKUP(A2001,Raw_Data!A2000:D4000,{2,3,4},0))} -> 45382 | C2001: 45385 | D2001: 45387 | E2001: Amit Joshi | F2001: Hyderabad | G2001: Telangana | H2001: Clothing | I2001: Jeans | J2001: 2 | K2001: 500 | L2001: =J2001*K2001 -> 1000 | M2001: Card | N2001: Pending | O2001: In Transit | P2001: WH-Delhi | Q2001: Online | R2001: N/A | S2001: N/A | T2001: 2 | U2001: =IF(COUNTIF(A2001:A4000,A2001)=1,"Keep","Duplicate") -> Keep | V2001: =IF(J2001<=0,"Fix","Ok") -> Ok | W2001: =IF(Raw_Data!K2001=0,"Missing","Valid") -> Valid | X2001: =IF(C2001<B2001,"Dispatch Error",IF(D2001<B2001,"Delivery Before Order",IF(D2001<C2001,"Delivery Before Dispatch","OK"))) -> OK | Y2001: =IF(K2001<=0,"Fix","Ok") -> Ok | Z2001: =IF(L2001="","Blank",IF(L2001=J2001*K2001,"Ok","Wrong")) -> Ok | AA2001: =IF(OR(L2001="",L2001<>J2001*K2001),J2001*K2001,L2001) -> 1000 | AB2001: =IF(M2001="","Missing","ok") -> ok | AC2001: =IF(R2001="No","Not Returned",IF(R2001="Yes",IF(S2001="","Unknown",S2001),IF(L2001<0,"Wrong",IF(OR(O2001="Delayed",O2001="In Transit",O2001="On Time"),"Not Returned","")))) -> Not Returned

Sheet Final_data
A1: Order_ID | B1: Order_Date | C1: Dispatch_Date | D1: Delivery_Date | E1: Customer_Name | F1: City | G1: State | H1: Product_Category | I1: Product_Name | J1: Quantity | K1: Unit_Price | L1: Total_Amount | M1: Payment_Mode | N1: Order_Status | O1: Delivery_Status | P1: Warehouse | Q1: Sales_Channel | R1: Return_Flag | S1: Return_Reason | T1: Delivery_Days | U1: Duplicate check | V1: Qty_Check_Status | W1: Unit_Price_Status | X1: Date_Status | Y1: Price_Check | Z1: Amount check | AA1: Final_Amount | AB1: Payment_Mode_check | AC1: Final_return_flag | AD1: Month | AE1: Year | AF1: Day_Name | AG1: Delivery_Performance | AH1: Delivery_Speed | AI1: Sales_Bucket | AJ1: Weekend_Order
A2: ORD00001 | B2: 45591 | C2: 45592 | D2: 45593 | E2: Karan Gupta | F2: Hyderabad | G2: Telangana | H2: Furniture | I2: Sofa | J2: 2 | K2: 100 | L2: 200 | M2: Card | N2: Pending | O2: Delayed | P2: WH-Delhi | Q2: Online | R2: No | S2: Late Delivery | T2: 1 | U2: Keep | V2: Ok | W2: Valid | X2: OK | Y2: Ok | Z2: Ok | AA2: 200 | AB2: ok | AC2: Not Returned | AD2: =TEXT(Sales_data[[#This Row],[Order_Date]],"MMM") -> Oct | AE2: =YEAR(C2) -> 2024 | AF2: =TEXT(Sales_data[[#This Row],[Order_Date]],"ddd") -> Sat | AG2: =IF(T2<=5,"On Time","Late") -> On Time | AH2: =IF(T2<=2,"Fast",IF(T2<=5,"Medium","Slow")) -> Fast | AI2: =IF(AA2>=5000,"High",IF(AA2>=2000,"Medium","Low")) -> Low | AJ2: =IF(AF2="Sat","Weekend",IF(AF2="Sun","Weekend","Weekday")) -> Weekend
A3: ORD00002 | B3: 45492 | C3: 45493 | D3: 45499 | E3: Sneha Singh | F3: Pune | G3: Maharashtra | H3: Grocery | I3: Oil | J3: 3 | K3: 2000 | L3: 6000 | M3: Card | N3: Pending | O3: On Time | P3: WH-Delhi | Q3: Offline | R3: Yes | S3: Late Delivery | T3: 6 | U3: Keep | V3: Ok | W3: Valid | X3: OK | Y3: Ok | Z3: Ok | AA3: 6000 | AB3: ok | AC3: Late Delivery | AD3: =TEXT(Sales_data[[#This Row],[Order_Date]],"MMM") -> Jul | AE3: =YEAR(C3) -> 2024 | AF3: =TEXT(Sales_data[[#This Row],[Order_Date]],"ddd") -> Fri | AG3: =IF(T3<=5,"On Time","Late") -> Late | AH3: =IF(T3<=2,"Fast",IF(T3<=5,"Medium","Slow")) -> Slow | AI3: =IF(AA3>=5000,"High",IF(AA3>=2000,"Medium","Low")) -> High | AJ3: =IF(AF3="Sat","Weekend",IF(AF3="Sun","Weekend","Weekday")) -> Weekday
A4: ORD00003 | B4: 45574 | C4: 45572 | D4: 45578 | E4: Karan Yadav | F4: Jaipur | G4: Rajasthan | H4: Furniture | I4: Table | J4: 1 | K4: 500 | L4: 500 | M4: UPI | N4: Completed | O4: Delayed | P4: WH-Pune | Q4: Online | R4: Yes | S4: Late Delivery | T4: 6 | U4: Keep | V4: Ok | W4: Valid | X4: Dispatch Error | Y4: Ok | Z4: Ok | AA4: 500 | AB4: ok | AC4: Late Delivery | AD4: =TEXT(Sales_data[[#This Row],[Order_Date]],"MMM") -> Oct | AE4: =YEAR(C4) -> 2024 | AF4: =TEXT(Sales_data[[#This Row],[Order_Date]],"ddd") -> Wed | AG4: =IF(T4<=5,"On Time","Late") -> Late | AH4: =IF(T4<=2,"Fast",IF(T4<=5,"Medium","Slow")) -> Slow | AI4: =IF(AA4>=5000,"High",IF(AA4>=2000,"Medium","Low")) -> Low | AJ4: =IF(AF4="Sat","Weekend",IF(AF4="Sun","Weekend","Weekday")) -> Weekday
A5: ORD00004 | B5: 45349 | C5: 45348 | D5: 45349 | E5: Neha Sharma | F5: Pune | G5: Maharashtra | H5: Furniture | I5: Table | J5: 1 | K5: 2000 | L5: 2000 | M5: Cash | N5: Completed | O5: Delayed | P5: WH-Delhi | Q5: Online | R5: No | S5: Late Delivery | T5: 1 | U5: Keep | V5: Ok | W5: Valid | X5: Dispatch Error | Y5: Ok | Z5: Ok | AA5: 2000 | AB5: ok | AC5: Not Returned | AD5: =TEXT(Sales_data[[#This Row],[Order_Date]],"MMM") -> Feb | AE5: =YEAR(C5) -> 2024 | AF5: =TEXT(Sales_data[[#This Row],[Order_Date]],"ddd") -> Tue | AG5: =IF(T5<=5,"On Time","Late") -> On Time | AH5: =IF(T5<=2,"Fast",IF(T5<=5,"Medium","Slow")) -> Fast | AI5: =IF(AA5>=5000,"High",IF(AA5>=2000,"Medium","Low")) -> Medium | AJ5: =IF(AF5="Sat","Weekend",IF(AF5="Sun","Weekend","Weekday")) -> Weekday
A6: ORD00005 | B6: 45502 | C6: 45503 | D6: 45503 | E6: Rahul Singh | F6: Bangalore | G6: Karnataka | H6: Clothing | I6: Jeans | J6: 1 | K6: 0 | L6: 0 | M6: Card | N6: Completed | O6: delayed | P6: WH-Delhi | Q6: Offline | R6: Yes | S6: Late Delivery | T6: 0 | U6: Keep | V6: Ok | W6: Missing | X6: OK | Y6: Fix | Z6: Ok | AA6: 0 | AB6: ok | AC6: Late Delivery | AD6: =TEXT(Sales_data[[#This Row],[Order_Date]],"MMM") -> Jul | AE6: =YEAR(C6) -> 2024 | AF6: =TEXT(Sales_data[[#This Row],[Order_Date]],"ddd") -> Mon | AG6: =IF(T6<=5,"On Time","Late") -> On Time | AH6: =IF(T6<=2,"Fast",IF(T6<=5,"Medium","Slow")) -> Fast | AI6: =IF(AA6>=5000,"High",IF(AA6>=2000,"Medium","Low")) -> Low | AJ6: =IF(AF6="Sat","Weekend",IF(AF6="Sun","Weekend","Weekday")) -> Weekday
A7: ORD00006 | B7: 45468 | C7: 45468 | D7: 45472 | E7: Vikas Joshi | F7: Jaipur | G7: Rajasthan | H7: Grocery | I7: Rice | J7: -1 | K7: 500 | L7: -500 | M7: Cash | N7: Completed | O7: In Transit | P7: WH-Delhi | Q7: Online | R7: No | S7: Late Delivery | T7: 4 | U7: Keep | V7: Fix | W7: Valid | X7: OK | Y7: Ok | Z7: Ok | AA7: -500 | AB7: ok | AC7: Not Returned | AD7: =TEXT(Sales_data[[#This Row],[Order_Date]],"MMM") -> Jun | AE7: =YEAR(C7) -> 2024 | AF7: =TEXT(Sales_data[[#This Row],[Order_Date]],"ddd") -> Tue | AG7: =IF(T7<=5,"On Time","Late") -> On Time | AH7: =IF(T7<=2,"Fast",IF(T7<=5,"Medium","Slow")) -> Medium | AI7: =IF(AA7>=5000,"High",IF(AA7>=2000,"Medium","Low")) -> Low | AJ7: =IF(AF7="Sat","Weekend",IF(AF7="Sun","Weekend","Weekday")) -> Weekday
A8: ORD00007 | B8: 45296 | C8: 45298 | D8: 45299 | E8: Karan Yadav | F8: Jaipur | G8: Rajasthan | H8: Furniture | I8: Chair | J8: 0 | K8: 2000 | L8: 0 | M8: UPI | N8: Completed | O8: Delayed | P8: WH-Mumbai | Q8: Online | R8: No | S8: Late Delivery | T8: 1 | U8: Keep | V8: Fix | W8: Valid | X8: OK | Y8: Ok | Z8: Ok | AA8: 0 | AB8: ok | AC8: Not Returned | AD8: =TEXT(Sales_data[[#This Row],[Order_Date]],"MMM") -> Jan | AE8: =YEAR(C8) -> 2024 | AF8: =TEXT(Sales_data[[#This Row],[Order_Date]],"ddd") -> Fri | AG8: =IF(T8<=5,"On Time","Late") -> On Time | AH8: =IF(T8<=2,"Fast",IF(T8<=5,"Medium","Slow")) -> Fast | AI8: =IF(AA8>=5000,"High",IF(AA8>=2000,"Medium","Low")) -> Low | AJ8: =IF(AF8="Sat","Weekend",IF(AF8="Sun","Weekend","Weekday")) -> Weekday
A9: ORD00008 | B9: 45612 | C9: 45614 | D9: 45616 | E9: Sneha Patel | F9: Nagpur | G9: Maharashtra | H9: Clothing | I9: T-Shirt | J9: 1 | K9: 0 | L9: 0 | M9: Card | N9: Cancelled | O9: On Time | P9: WH-Pune | Q9: Online | R9: yes | S9: Late Delivery | T9: 2 | U9: Keep | V9: Ok | W9: Missing | X9: OK | Y9: Fix | Z9: Ok | AA9: 0 | AB9: ok | AC9: Late Delivery | AD9: =TEXT(Sales_data[[#This Row],[Order_Date]],"MMM") -> Nov | AE9: =YEAR(C9) -> 2024 | AF9: =TEXT(Sales_data[[#This Row],[Order_Date]],"ddd") -> Sat | AG9: =IF(T9<=5,"On Time","Late") -> On Time | AH9: =IF(T9<=2,"Fast",IF(T9<=5,"Medium","Slow")) -> Fast | AI9: =IF(AA9>=5000,"High",IF(AA9>=2000,"Medium","Low")) -> Low | AJ9: =IF(AF9="Sat","Weekend",IF(AF9="Sun","Weekend","Weekday")) -> Weekend
A10: ORD00009 | B10: 45346 | C10: 45344 | D10: 45349 | E10: Rahul Joshi | F10: Bangalore | G10: Karnataka | H10: Clothing | I10: T-Shirt | J10: 2 | K10: 100 | L10: 200 | M10: UPI | N10: Completed | O10: On Time | P10: WH-Pune | Q10: Online | R10: yes | S10: Late Delivery | T10: 5 | U10: Keep | V10: Ok | W10: Valid | X10: Dispatch Error | Y10: Ok | Z10: Ok | AA10: 200 | AB10: ok | AC10: Late Delivery | AD10: =TEXT(Sales_data[[#This Row],[Order_Date]],"MMM") -> Feb | AE10: =YEAR(C10) -> 2024 | AF10: =TEXT(Sales_data[[#This Row],[Order_Date]],"ddd") -> Sat | AG10: =IF(T10<=5,"On Time","Late") -> On Time | AH10: =IF(T10<=2,"Fast",IF(T10<=5,"Medium","Slow")) -> Medium | AI10: =IF(AA10>=5000,"High",IF(AA10>=2000,"Medium","Low")) -> Low | AJ10: =IF(AF10="Sat","Weekend",IF(AF10="Sun","Weekend","Weekday")) -> Weekend
A11: ORD00010 | B11: 45641 | C11: 45644 | D11: 45644 | E11: Rahul Singh | F11: Pune | G11: Maharashtra | H11: Furniture | I11: Sofa | J11: -1 | K11: 1000 | L11: -1000 | M11: Unknown | N11: Completed | O11: Delayed | P11: WH-Pune | Q11: Online | R11: Yes | S11: Late Delivery | T11: 0 | U11: Keep | V11: Fix | W11: Valid | X11: OK | Y11: Ok | Z11: Ok | AA11: -1000 | AB11: ok | AC11: Late Delivery | AD11: =TEXT(Sales_data[[#This Row],[Order_Date]],"MMM") -> Dec | AE11: =YEAR(C11) -> 2024 | AF11: =TEXT(Sales_data[[#This Row],[Order_Date]],"ddd") -> Sun | AG11: =IF(T11<=5,"On Time","Late") -> On Time | AH11: =IF(T11<=2,"Fast",IF(T11<=5,"Medium","Slow")) -> Fast | AI11: =IF(AA11>=5000,"High",IF(AA11>=2000,"Medium","Low")) -> Low | AJ11: =IF(AF11="Sat","Weekend",IF(AF11="Sun","Weekend","Weekday")) -> Weekend
A12: ORD00011 | B12: 45579 | C12: 45578 | D12: 45577 | E12: Vikas Yadav | F12: Hyderabad | G12: Telangana | H12: Grocery | I12: Oil | J12: 2 | K12: 2000 | L12: 4000 | M12: Unknown | N12: Completed | O12: Delayed | P12: WH-Pune | Q12: Online | R12: No | S12: N/A | T12: -1 | U12: Keep | V12: Ok | W12: Valid | X12: Dispatch Error | Y12: Ok | Z12: Ok | AA12: 4000 | AB12: ok | AC12: Not Returned | AD12: =TEXT(Sales_data[[#This Row],[Order_Date]],"MMM") -> Oct | AE12: =YEAR(C12) -> 2024 | AF12: =TEXT(Sales_data[[#This Row],[Order_Date]],"ddd") -> Mon | AG12: =IF(T12<=5,"On Time","Late") -> On Time | AH12: =IF(T12<=2,"Fast",IF(T12<=5,"Medium","Slow")) -> Fast | AI12: =IF(AA12>=5000,"High",IF(AA12>=2000,"Medium","Low")) -> Medium | AJ12: =IF(AF12="Sat","Weekend",IF(AF12="Sun","Weekend","Weekday")) -> Weekday
A13: ORD00012 | B13: 45465 | C13: 45463 | D13: 45464 | E13: Amit Gupta | F13: Pune | G13: Maharashtra | H13: Furniture | I13: Sofa | J13: 0 | K13: 0 | L13: 0 | M13: Card | N13: Cancelled | O13: Delayed | P13: WH-Mumbai | Q13: Online | R13: Yes | S13: Late Delivery | T13: 1 | U13: Keep | V13: Fix | W13: Missing | X13: Dispatch Error | Y13: Fix | Z13: Ok | AA13: 0 | AB13: ok | AC13: Late Delivery | AD13: =TEXT(Sales_data[[#This Row],[Order_Date]],"MMM") -> Jun | AE13: =YEAR(C13) -> 2024 | AF13: =TEXT(Sales_data[[#This Row],[Order_Date]],"ddd") -> Sat | AG13: =IF(T13<=5,"On Time","Late") -> On Time | AH13: =IF(T13<=2,"Fast",IF(T13<=5,"Medium","Slow")) -> Fast | AI13: =IF(AA13>=5000,"High",IF(AA13>=2000,"Medium","Low")) -> Low | AJ13: =IF(AF13="Sat","Weekend",IF(AF13="Sun","Weekend","Weekday")) -> Weekend
... A2001: ORD02000 | B2001: 45382 | C2001: 45385 | D2001: 45387 | E2001: Amit Joshi | F2001: Hyderabad | G2001: Telangana | H2001: Clothing | I2001: Jeans | J2001: 2 | K2001: 500 | L2001: 1000 | M2001: Card | N2001: Pending | O2001: In Transit | P2001: WH-Delhi | Q2001: Online | R2001: N/A | S2001: N/A | T2001: 2 | U2001: Keep | V2001: Ok | W2001: Valid | X2001: OK | Y2001: Ok | Z2001: Ok | AA2001: 1000 | AB2001: ok | AC2001: Not Returned | AD2001: =TEXT(Sales_data[[#This Row],[Order_Date]],"MMM") -> Mar | AE2001: =YEAR(C2001) -> 2024 | AF2001: =TEXT(Sales_data[[#This Row],[Order_Date]],"ddd") -> Sun | AG2001: =IF(T2001<=5,"On Time","Late") -> On Time | AH2001: =IF(T2001<=2,"Fast",IF(T2001<=5,"Medium","Slow")) -> Fast | AI2001: =IF(AA2001>=5000,"High",IF(AA2001>=2000,"Medium","Low")) -> Low | AJ2001: =IF(AF2001="Sat","Weekend",IF(AF2001="Sun","Weekend","Weekday")) -> Weekend

Sheet Pivote_data
A2: Monthly revenue
A3: Months | B3: Final Amount
A4: Feb | B4: 3700
A5: Mar | B5: 21300
A6: Apr | B6: 8800
A7: Jul | B7: 11500
A8: Aug | B8: 26200
A9: Oct | B9: 17600
A10: Dec | B10: 14300
A11: Grand Total | B11: 103400
A18: Revenue by Product Category
A19: Product category | B19: Final_Amount
A20: Furniture | B20: 103400
A21: Grand Total | B21: 103400
A28: Orders by State
A29: Row Labels | B29: Count of Order_ID
A30: Delhi | B30: 24
A31: Karnataka | B31: 20
A32: Maharashtra | B32: 48
A33: Rajasthan | B33: 7
A34: Telangana | B34: 15
A35: Uttar Pradesh | B35: 16
A36: Grand Total | B36: 130
A39: Payment Mode
A40: Row Labels | B40: Count of Order_ID
A41: Card | B41: 57
A42: UPI | B42: 73
A43: Grand Total | B43: 130
A48: Delivery Performance
A49: Row Labels | B49: Count of Order_ID
A50: Late | B50: 31
A51: On Time | B51: 99
A52: Grand Total | B52: 130
A57: Sales Bucket
A58: Row Labels | B58: Count of Order_ID
A59: High | B59: 5
A60: Low | B60: 103
A61: Medium | B61: 22
A62: Grand Total | B62: 130

Sheet Dashboard
Q5: =COUNTIF(Sales_data[[#All],[Delivery_Performance]],"On Time")/COUNTA(Sales_data[Order_ID]) -> 0.7745
G6: =COUNTA(Sales_data[Order_ID]) -> 2000 | I6: =SUM(Sales_data[Final_Amount]) -> 1417100 | L6: =SUM(Sales_data[Quantity]) -> 2024
N8: =AVERAGE(Sales_data[Delivery_Days]) -> 3.033
